setup.py
probability_function_dsnd/Binomialdistribution.py
probability_function_dsnd/Gaussiandistribution.py
probability_function_dsnd/Generaldistribution.py
probability_function_dsnd/__init__.py
probability_function_dsnd.egg-info/PKG-INFO
probability_function_dsnd.egg-info/SOURCES.txt
probability_function_dsnd.egg-info/dependency_links.txt
probability_function_dsnd.egg-info/not-zip-safe
probability_function_dsnd.egg-info/top_level.txt