Metadata-Version: 1.0
Name: probability-function-dsnd
Version: 0.1
Summary: Gaussian and Binomial distributions
Home-page: UNKNOWN
Author: Melanija Gerasimovska
Author-email: melanija_gerasimovska@hotmail.com
License: UNKNOWN
Platform: UNKNOWN
